tabswitcher/NetworkImage.py
tabswitcher/SearchInput.py
tabswitcher/Settings.py
tabswitcher/Tab.py
tabswitcher/TabList.py
tabswitcher/VisibilityChecker.py
tabswitcher/__main__.py
tabswitcher/actions.py
tabswitcher/brotab.py
tabswitcher/colors.py
tabswitcher/firefoxHelper.py
tabswitcher/focusWindow.py
tabswitcher/fuzzySearch.py
tabswitcher/loadBookmarks.py
tabswitcher/loadHistory.py
tabswitcher/logTabs.py
tabswitcher/shortcuts.py
tabswitcher/assets/Icon.ico
tabswitcher/assets/install.sh
tabswitcher/assets/runLogger.vbs
tabswitcher/assets/sans.ttf
tabswitcher/assets/searchIcon.svg
tabswitcher/assets/tabswitcher_service.xml
tabswitcher/assets/uninstall.sh
tabswitcher-0.1.11.dist-info/LICENCE
tabswitcher-0.1.11.dist-info/METADATA
tabswitcher-0.1.11.dist-info/WHEEL
tabswitcher-0.1.11.dist-info/entry_points.txt
tabswitcher-0.1.11.dist-info/top_level.txt
tabswitcher-0.1.11.dist-info/RECORD
