Metadata-Version: 2.1
Name: tabswitcher
Version: 0.1.11
Summary: A tool for efficient browser tab switching outside the browser
Home-page: https://github.com/YukiGasai/tabswitcher
Author: YukiGasai
Author-email: r.lindede@googlemail.com
License: AGPL-3.0
Keywords: tabswitcher,browsertool,tool
Classifier: Development Status :: 3 - Alpha
Classifier: Intended Audience :: Developers
Classifier: License :: OSI Approved :: GNU Affero General Public License v3
Classifier: Programming Language :: Python :: 3
Classifier: Programming Language :: Python :: 3.7
Classifier: Programming Language :: Python :: 3.8
Classifier: Programming Language :: Python :: 3.9
Classifier: Programming Language :: Python :: 3.10
Classifier: Programming Language :: Python :: 3.11
License-File: LICENCE
Requires-Dist: werkzeug <3.0
Requires-Dist: fuzzyfinder
Requires-Dist: PyQt5
Requires-Dist: schedule
Requires-Dist: pynput ; platform_system == "Windows"
Requires-Dist: pywin32 ; platform_system == "Windows"
Requires-Dist: pyWinhook ; platform_system == "Windows"
